delay_finder/__init__.py
delay_finder/data_split.py
delay_finder/filter_columns.py
delay_finder/load_and_save.py
delay_finder/make_histogram.py
delay_finder/read.py
delay_finder/replace_value.py
delay_finder-1.0.2.dist-info/LICENSE
delay_finder-1.0.2.dist-info/METADATA
delay_finder-1.0.2.dist-info/WHEEL
delay_finder-1.0.2.dist-info/RECORD
