Metadata-Version: 2.1
Name: delay_finder
Version: 1.0.2
Summary: Analyze and predict airline delays!
License: MIT
Author: Siddharth Balodi, Charles Benkard, Mikel Ibarra Gallardo, and Stephanie Ta
Requires-Python: >=3.9
Classifier: License :: OSI Approved :: MIT License
Classifier: Programming Language :: Python :: 3
Classifier: Programming Language :: Python :: 3.9
Classifier: Programming Language :: Python :: 3.10
Classifier: Programming Language :: Python :: 3.11
Classifier: Programming Language :: Python :: 3.12
Requires-Dist: altair (>=5.2.0)
Requires-Dist: pandas (>=2.2.0)
Requires-Dist: scikit-learn (>=1.4.0)
